README.md
setup.py
gmtool/__init__.py
gmtool/re_generation.py
gmtool.egg-info/PKG-INFO
gmtool.egg-info/SOURCES.txt
gmtool.egg-info/dependency_links.txt
gmtool.egg-info/requires.txt
gmtool.egg-info/top_level.txt