Metadata-Version: 2.1
Name: gmtool
Version: 1.0.2
Summary: A powerful generation tool
Home-page: https://www.python.org/
Author: Gmwang
Author-email: 550146647@qq.com
License: MIT
Project-URL: Documentation, https://www.apple.com.cn/
Project-URL: Funding, https://www.apple.com.cn/
Project-URL: Source, https://www.apple.com.cn/
Project-URL: Tracker, https://www.apple.com.cn/
Keywords: generation
Platform: UNKNOWN
Requires-Python: >=3
